[
	{
		"__TYPE__": "SharedSliceContent",
		"variation": "default",
		"primary": {
			"heading": {
				"__TYPE__": "FieldContent",
				"value": "stomach",
				"type": "Text"
			}
		},
		"items": [
			{
				"__TYPE__": "GroupItemContent",
				"value": [
					[
						"tech_name",
						{
							"__TYPE__": "FieldContent",
							"value": "air",
							"type": "Text"
						}
					],
					[
						"tech_color",
						{
							"__TYPE__": "FieldContent",
							"value": "#5627ea",
							"type": "Color"
						}
					]
				]
			}
		]
	}
]